Workbook

Sheet README
A1: Bluebell SaaS Pte Ltd - operating model
A2: Source: data/financials.xlsx (36 months, Oct-2023 to 2026-09). Opening active customers = 120, per management.
A5: How to use
A6: Blue cells are inputs. Everything else is a live formula - change a driver and the whole model recalculates.
A7: Input_Data is the only sheet with pasted numbers. Replace it with a fresh extract each month; all other tabs follow.
A9: Definitions used
A10: Active customers opening + new - churned, seeded at 120
A11: ARPA MRR / period-end active customers
A12: Gross margin (MRR - COGS) / MRR
A13: Logo churn churned customers / opening customers, monthly
A14: CAC trailing-12-month S&M / trailing-12-month NEW customers (no netting of churn)
A15: LTV ARPA x trailing-12-month gross margin / trailing-12-month logo churn rate
... A24: The extract behaves like normalised management data rather than a raw ledger: gross margin rises by exactly 17.1 basis points in every one of the 36 months (72.00% to 78.00%), and churned-customer counts step up on a fixed cadence. Worth reconciling to the accounting system before external use.

Sheet Assumptions
A1: Assumptions & drivers
A2: Blue = input. Edit these; the model follows.
A4: Driver | B4: Value | C4: Basis
A5: Opening active customers (Oct-2023) | B5: 120 | C5: Given by management; seeds the whole customer roll-forward.
A6: Projection: monthly growth in new logos | B6: 0.026372995 | C6: Trailing-12-month CAGR of monthly new customers.
A7: Projection: monthly logo churn rate | B7: 0.02255431 | C7: Trailing-12-month churn; held flat (conservative - the trend is improving).
A8: Projection: monthly ARPA growth | B8: 0.0071571798 | C8: Trailing-12-month CAGR of ARPA.
A9: Projection: gross margin | B9: 0.77999997 | C9: Latest month; held flat rather than extrapolating the upward trend.
A10: Projection: CAC per new logo | B10: 1172.9147 | C10: Latest trailing-12-month CAC; drives projected S&M spend.
A11: Benchmark: CAC payback target (months) | B11: 12 | C11: Common venture benchmark.
A12: Benchmark: LTV:CAC target | B12: 3 | C12: Common venture benchmark.
A13: Benchmark: magic number threshold | B13: 0.75 | C13: Above 0.75 = keep spending.

Sheet Input_Data
A1: Input data (as supplied)
A2: Pasted from data/financials.xlsx - the only hardcoded numbers in the model.
A4: Month | B4: MRR | C4: New customers | D4: Churned customers | E4: COGS | F4: S&M spend | G4: Headcount
A5: 2023-10 | B5: 22955.41 | C5: 14 | D5: 4 | E5: 6427.51 | F5: 12146.46 | G5: 9
A6: 2023-11 | B6: 25680.63 | C6: 14 | D6: 4 | E6: 7146.55 | F6: 13079.62 | G6: 10
A7: 2023-12 | B7: 27600.88 | C7: 17 | D7: 4 | E7: 7633.61 | F7: 15396.65 | G7: 10
A8: 2024-01 | B8: 29838.64 | C8: 15 | D8: 5 | E8: 8201.36 | F8: 13897.61 | G8: 11
A9: 2024-02 | B9: 31936.87 | C9: 15 | D9: 5 | E9: 8723.33 | F9: 14350.37 | G9: 12
A10: 2024-03 | B10: 34682.07 | C10: 18 | D10: 5 | E10: 9413.7 | F10: 17213.82 | G10: 13
A11: 2024-04 | B11: 37305.89 | C11: 20 | D11: 6 | E11: 10061.93 | F11: 19959.66 | G11: 13
A12: 2024-05 | B12: 40825.45 | C12: 20 | D12: 6 | E12: 10941.22 | F12: 18141.63 | G12: 14
A13: 2024-06 | B13: 44263.07 | C13: 22 | D13: 6 | E13: 11786.62 | F13: 19920.09 | G13: 15
A14: 2024-07 | B14: 47951.09 | C14: 19 | D14: 7 | E14: 12686.49 | F14: 18873.83 | G14: 15
A15: 2024-08 | B15: 51330.25 | C15: 23 | D15: 7 | E15: 13492.52 | F15: 22802.84 | G15: 16
A16: 2024-09 | B16: 54420.02 | C16: 24 | D16: 7 | E16: 14211.4 | F16: 24061.55 | G16: 17
... A40: 2026-09 | B40: 178857.07 | C40: 41 | D40: 15 | E40: 39348.56 | F40: 48686.47 | G40: 34

Sheet Monthly_Metrics
A1: Monthly metrics
A2: Every cell is a formula off Input_Data and Assumptions. TTM columns start once 12 months of history exist.
A4: Month | B4: Customers opening | C4: New | D4: Churned | E4: Net adds | F4: Customers closing | G4: MRR | H4: MoM growth | I4: YoY growth | J4: ARR | K4: COGS | L4: Gross profit | M4: Gross margin | N4: ARPA | O4: Logo churn | P4: S&M spend | Q4: CAC (month) | R4: CAC (TTM) | S4: Gross margin (TTM) | T4: Logo churn (TTM) | U4: Implied life (mo) | V4: LTV | W4: LTV : CAC | X4: CAC payback (mo) | Y4: Contribution | Z4: Contribution margin | AA4: Headcount | AB4: ARR per FTE
A5: =Input_Data!A5 | B5: =Assumptions!$B$5 | C5: =Input_Data!C5 | D5: =Input_Data!D5 | E5: =C5-D5 | F5: =B5+E5 | G5: =Input_Data!B5 | J5: =G5*12 | K5: =Input_Data!E5 | L5: =G5-K5 | M5: =L5/G5 | N5: =G5/F5 | O5: =D5/B5 | P5: =Input_Data!F5 | Q5: =P5/C5 | Y5: =G5-K5-P5 | Z5: =Y5/G5 | AA5: =Input_Data!G5 | AB5: =J5/AA5
A6: =Input_Data!A6 | B6: =F5 | C6: =Input_Data!C6 | D6: =Input_Data!D6 | E6: =C6-D6 | F6: =B6+E6 | G6: =Input_Data!B6 | H6: =G6/G5-1 | J6: =G6*12 | K6: =Input_Data!E6 | L6: =G6-K6 | M6: =L6/G6 | N6: =G6/F6 | O6: =D6/B6 | P6: =Input_Data!F6 | Q6: =P6/C6 | Y6: =G6-K6-P6 | Z6: =Y6/G6 | AA6: =Input_Data!G6 | AB6: =J6/AA6
A7: =Input_Data!A7 | B7: =F6 | C7: =Input_Data!C7 | D7: =Input_Data!D7 | E7: =C7-D7 | F7: =B7+E7 | G7: =Input_Data!B7 | H7: =G7/G6-1 | J7: =G7*12 | K7: =Input_Data!E7 | L7: =G7-K7 | M7: =L7/G7 | N7: =G7/F7 | O7: =D7/B7 | P7: =Input_Data!F7 | Q7: =P7/C7 | Y7: =G7-K7-P7 | Z7: =Y7/G7 | AA7: =Input_Data!G7 | AB7: =J7/AA7
A8: =Input_Data!A8 | B8: =F7 | C8: =Input_Data!C8 | D8: =Input_Data!D8 | E8: =C8-D8 | F8: =B8+E8 | G8: =Input_Data!B8 | H8: =G8/G7-1 | J8: =G8*12 | K8: =Input_Data!E8 | L8: =G8-K8 | M8: =L8/G8 | N8: =G8/F8 | O8: =D8/B8 | P8: =Input_Data!F8 | Q8: =P8/C8 | Y8: =G8-K8-P8 | Z8: =Y8/G8 | AA8: =Input_Data!G8 | AB8: =J8/AA8
A9: =Input_Data!A9 | B9: =F8 | C9: =Input_Data!C9 | D9: =Input_Data!D9 | E9: =C9-D9 | F9: =B9+E9 | G9: =Input_Data!B9 | H9: =G9/G8-1 | J9: =G9*12 | K9: =Input_Data!E9 | L9: =G9-K9 | M9: =L9/G9 | N9: =G9/F9 | O9: =D9/B9 | P9: =Input_Data!F9 | Q9: =P9/C9 | Y9: =G9-K9-P9 | Z9: =Y9/G9 | AA9: =Input_Data!G9 | AB9: =J9/AA9
A10: =Input_Data!A10 | B10: =F9 | C10: =Input_Data!C10 | D10: =Input_Data!D10 | E10: =C10-D10 | F10: =B10+E10 | G10: =Input_Data!B10 | H10: =G10/G9-1 | J10: =G10*12 | K10: =Input_Data!E10 | L10: =G10-K10 | M10: =L10/G10 | N10: =G10/F10 | O10: =D10/B10 | P10: =Input_Data!F10 | Q10: =P10/C10 | Y10: =G10-K10-P10 | Z10: =Y10/G10 | AA10: =Input_Data!G10 | AB10: =J10/AA10
A11: =Input_Data!A11 | B11: =F10 | C11: =Input_Data!C11 | D11: =Input_Data!D11 | E11: =C11-D11 | F11: =B11+E11 | G11: =Input_Data!B11 | H11: =G11/G10-1 | J11: =G11*12 | K11: =Input_Data!E11 | L11: =G11-K11 | M11: =L11/G11 | N11: =G11/F11 | O11: =D11/B11 | P11: =Input_Data!F11 | Q11: =P11/C11 | Y11: =G11-K11-P11 | Z11: =Y11/G11 | AA11: =Input_Data!G11 | AB11: =J11/AA11
A12: =Input_Data!A12 | B12: =F11 | C12: =Input_Data!C12 | D12: =Input_Data!D12 | E12: =C12-D12 | F12: =B12+E12 | G12: =Input_Data!B12 | H12: =G12/G11-1 | J12: =G12*12 | K12: =Input_Data!E12 | L12: =G12-K12 | M12: =L12/G12 | N12: =G12/F12 | O12: =D12/B12 | P12: =Input_Data!F12 | Q12: =P12/C12 | Y12: =G12-K12-P12 | Z12: =Y12/G12 | AA12: =Input_Data!G12 | AB12: =J12/AA12
A13: =Input_Data!A13 | B13: =F12 | C13: =Input_Data!C13 | D13: =Input_Data!D13 | E13: =C13-D13 | F13: =B13+E13 | G13: =Input_Data!B13 | H13: =G13/G12-1 | J13: =G13*12 | K13: =Input_Data!E13 | L13: =G13-K13 | M13: =L13/G13 | N13: =G13/F13 | O13: =D13/B13 | P13: =Input_Data!F13 | Q13: =P13/C13 | Y13: =G13-K13-P13 | Z13: =Y13/G13 | AA13: =Input_Data!G13 | AB13: =J13/AA13
A14: =Input_Data!A14 | B14: =F13 | C14: =Input_Data!C14 | D14: =Input_Data!D14 | E14: =C14-D14 | F14: =B14+E14 | G14: =Input_Data!B14 | H14: =G14/G13-1 | J14: =G14*12 | K14: =Input_Data!E14 | L14: =G14-K14 | M14: =L14/G14 | N14: =G14/F14 | O14: =D14/B14 | P14: =Input_Data!F14 | Q14: =P14/C14 | Y14: =G14-K14-P14 | Z14: =Y14/G14 | AA14: =Input_Data!G14 | AB14: =J14/AA14
A15: =Input_Data!A15 | B15: =F14 | C15: =Input_Data!C15 | D15: =Input_Data!D15 | E15: =C15-D15 | F15: =B15+E15 | G15: =Input_Data!B15 | H15: =G15/G14-1 | J15: =G15*12 | K15: =Input_Data!E15 | L15: =G15-K15 | M15: =L15/G15 | N15: =G15/F15 | O15: =D15/B15 | P15: =Input_Data!F15 | Q15: =P15/C15 | Y15: =G15-K15-P15 | Z15: =Y15/G15 | AA15: =Input_Data!G15 | AB15: =J15/AA15
A16: =Input_Data!A16 | B16: =F15 | C16: =Input_Data!C16 | D16: =Input_Data!D16 | E16: =C16-D16 | F16: =B16+E16 | G16: =Input_Data!B16 | H16: =G16/G15-1 | J16: =G16*12 | K16: =Input_Data!E16 | L16: =G16-K16 | M16: =L16/G16 | N16: =G16/F16 | O16: =D16/B16 | P16: =Input_Data!F16 | Q16: =P16/C16 | R16: =SUM(P5:P16)/SUM(C5:C16) | S16: =(SUM(G5:G16)-SUM(K5:K16))/SUM(G5:G16) | T16: =SUM(D5:D16)/SUM(B5:B16) | U16: =1/T16 | V16: =N16*S16/T16 | W16: =V16/R16 | X16: =R16/(N16*S16) | Y16: =G16-K16-P16 | Z16: =Y16/G16 | AA16: =Input_Data!G16 | AB16: =J16/AA16
A17: =Input_Data!A17 | B17: =F16 | C17: =Input_Data!C17 | D17: =Input_Data!D17 | E17: =C17-D17 | F17: =B17+E17 | G17: =Input_Data!B17 | H17: =G17/G16-1 | I17: =G17/G5-1 | J17: =G17*12 | K17: =Input_Data!E17 | L17: =G17-K17 | M17: =L17/G17 | N17: =G17/F17 | O17: =D17/B17 | P17: =Input_Data!F17 | Q17: =P17/C17 | R17: =SUM(P6:P17)/SUM(C6:C17) | S17: =(SUM(G6:G17)-SUM(K6:K17))/SUM(G6:G17) | T17: =SUM(D6:D17)/SUM(B6:B17) | U17: =1/T17 | V17: =N17*S17/T17 | W17: =V17/R17 | X17: =R17/(N17*S17) | Y17: =G17-K17-P17 | Z17: =Y17/G17 | AA17: =Input_Data!G17 | AB17: =J17/AA17
A18: =Input_Data!A18 | B18: =F17 | C18: =Input_Data!C18 | D18: =Input_Data!D18 | E18: =C18-D18 | F18: =B18+E18 | G18: =Input_Data!B18 | H18: =G18/G17-1 | I18: =G18/G6-1 | J18: =G18*12 | K18: =Input_Data!E18 | L18: =G18-K18 | M18: =L18/G18 | N18: =G18/F18 | O18: =D18/B18 | P18: =Input_Data!F18 | Q18: =P18/C18 | R18: =SUM(P7:P18)/SUM(C7:C18) | S18: =(SUM(G7:G18)-SUM(K7:K18))/SUM(G7:G18) | T18: =SUM(D7:D18)/SUM(B7:B18) | U18: =1/T18 | V18: =N18*S18/T18 | W18: =V18/R18 | X18: =R18/(N18*S18) | Y18: =G18-K18-P18 | Z18: =Y18/G18 | AA18: =Input_Data!G18 | AB18: =J18/AA18
A19: =Input_Data!A19 | B19: =F18 | C19: =Input_Data!C19 | D19: =Input_Data!D19 | E19: =C19-D19 | F19: =B19+E19 | G19: =Input_Data!B19 | H19: =G19/G18-1 | I19: =G19/G7-1 | J19: =G19*12 | K19: =Input_Data!E19 | L19: =G19-K19 | M19: =L19/G19 | N19: =G19/F19 | O19: =D19/B19 | P19: =Input_Data!F19 | Q19: =P19/C19 | R19: =SUM(P8:P19)/SUM(C8:C19) | S19: =(SUM(G8:G19)-SUM(K8:K19))/SUM(G8:G19) | T19: =SUM(D8:D19)/SUM(B8:B19) | U19: =1/T19 | V19: =N19*S19/T19 | W19: =V19/R19 | X19: =R19/(N19*S19) | Y19: =G19-K19-P19 | Z19: =Y19/G19 | AA19: =Input_Data!G19 | AB19: =J19/AA19
A20: =Input_Data!A20 | B20: =F19 | C20: =Input_Data!C20 | D20: =Input_Data!D20 | E20: =C20-D20 | F20: =B20+E20 | G20: =Input_Data!B20 | H20: =G20/G19-1 | I20: =G20/G8-1 | J20: =G20*12 | K20: =Input_Data!E20 | L20: =G20-K20 | M20: =L20/G20 | N20: =G20/F20 | O20: =D20/B20 | P20: =Input_Data!F20 | Q20: =P20/C20 | R20: =SUM(P9:P20)/SUM(C9:C20) | S20: =(SUM(G9:G20)-SUM(K9:K20))/SUM(G9:G20) | T20: =SUM(D9:D20)/SUM(B9:B20) | U20: =1/T20 | V20: =N20*S20/T20 | W20: =V20/R20 | X20: =R20/(N20*S20) | Y20: =G20-K20-P20 | Z20: =Y20/G20 | AA20: =Input_Data!G20 | AB20: =J20/AA20
A21: =Input_Data!A21 | B21: =F20 | C21: =Input_Data!C21 | D21: =Input_Data!D21 | E21: =C21-D21 | F21: =B21+E21 | G21: =Input_Data!B21 | H21: =G21/G20-1 | I21: =G21/G9-1 | J21: =G21*12 | K21: =Input_Data!E21 | L21: =G21-K21 | M21: =L21/G21 | N21: =G21/F21 | O21: =D21/B21 | P21: =Input_Data!F21 | Q21: =P21/C21 | R21: =SUM(P10:P21)/SUM(C10:C21) | S21: =(SUM(G10:G21)-SUM(K10:K21))/SUM(G10:G21) | T21: =SUM(D10:D21)/SUM(B10:B21) | U21: =1/T21 | V21: =N21*S21/T21 | W21: =V21/R21 | X21: =R21/(N21*S21) | Y21: =G21-K21-P21 | Z21: =Y21/G21 | AA21: =Input_Data!G21 | AB21: =J21/AA21
A22: =Input_Data!A22 | B22: =F21 | C22: =Input_Data!C22 | D22: =Input_Data!D22 | E22: =C22-D22 | F22: =B22+E22 | G22: =Input_Data!B22 | H22: =G22/G21-1 | I22: =G22/G10-1 | J22: =G22*12 | K22: =Input_Data!E22 | L22: =G22-K22 | M22: =L22/G22 | N22: =G22/F22 | O22: =D22/B22 | P22: =Input_Data!F22 | Q22: =P22/C22 | R22: =SUM(P11:P22)/SUM(C11:C22) | S22: =(SUM(G11:G22)-SUM(K11:K22))/SUM(G11:G22) | T22: =SUM(D11:D22)/SUM(B11:B22) | U22: =1/T22 | V22: =N22*S22/T22 | W22: =V22/R22 | X22: =R22/(N22*S22) | Y22: =G22-K22-P22 | Z22: =Y22/G22 | AA22: =Input_Data!G22 | AB22: =J22/AA22
A23: =Input_Data!A23 | B23: =F22 | C23: =Input_Data!C23 | D23: =Input_Data!D23 | E23: =C23-D23 | F23: =B23+E23 | G23: =Input_Data!B23 | H23: =G23/G22-1 | I23: =G23/G11-1 | J23: =G23*12 | K23: =Input_Data!E23 | L23: =G23-K23 | M23: =L23/G23 | N23: =G23/F23 | O23: =D23/B23 | P23: =Input_Data!F23 | Q23: =P23/C23 | R23: =SUM(P12:P23)/SUM(C12:C23) | S23: =(SUM(G12:G23)-SUM(K12:K23))/SUM(G12:G23) | T23: =SUM(D12:D23)/SUM(B12:B23) | U23: =1/T23 | V23: =N23*S23/T23 | W23: =V23/R23 | X23: =R23/(N23*S23) | Y23: =G23-K23-P23 | Z23: =Y23/G23 | AA23: =Input_Data!G23 | AB23: =J23/AA23
A24: =Input_Data!A24 | B24: =F23 | C24: =Input_Data!C24 | D24: =Input_Data!D24 | E24: =C24-D24 | F24: =B24+E24 | G24: =Input_Data!B24 | H24: =G24/G23-1 | I24: =G24/G12-1 | J24: =G24*12 | K24: =Input_Data!E24 | L24: =G24-K24 | M24: =L24/G24 | N24: =G24/F24 | O24: =D24/B24 | P24: =Input_Data!F24 | Q24: =P24/C24 | R24: =SUM(P13:P24)/SUM(C13:C24) | S24: =(SUM(G13:G24)-SUM(K13:K24))/SUM(G13:G24) | T24: =SUM(D13:D24)/SUM(B13:B24) | U24: =1/T24 | V24: =N24*S24/T24 | W24: =V24/R24 | X24: =R24/(N24*S24) | Y24: =G24-K24-P24 | Z24: =Y24/G24 | AA24: =Input_Data!G24 | AB24: =J24/AA24
A25: =Input_Data!A25 | B25: =F24 | C25: =Input_Data!C25 | D25: =Input_Data!D25 | E25: =C25-D25 | F25: =B25+E25 | G25: =Input_Data!B25 | H25: =G25/G24-1 | I25: =G25/G13-1 | J25: =G25*12 | K25: =Input_Data!E25 | L25: =G25-K25 | M25: =L25/G25 | N25: =G25/F25 | O25: =D25/B25 | P25: =Input_Data!F25 | Q25: =P25/C25 | R25: =SUM(P14:P25)/SUM(C14:C25) | S25: =(SUM(G14:G25)-SUM(K14:K25))/SUM(G14:G25) | T25: =SUM(D14:D25)/SUM(B14:B25) | U25: =1/T25 | V25: =N25*S25/T25 | W25: =V25/R25 | X25: =R25/(N25*S25) | Y25: =G25-K25-P25 | Z25: =Y25/G25 | AA25: =Input_Data!G25 | AB25: =J25/AA25
A26: =Input_Data!A26 | B26: =F25 | C26: =Input_Data!C26 | D26: =Input_Data!D26 | E26: =C26-D26 | F26: =B26+E26 | G26: =Input_Data!B26 | H26: =G26/G25-1 | I26: =G26/G14-1 | J26: =G26*12 | K26: =Input_Data!E26 | L26: =G26-K26 | M26: =L26/G26 | N26: =G26/F26 | O26: =D26/B26 | P26: =Input_Data!F26 | Q26: =P26/C26 | R26: =SUM(P15:P26)/SUM(C15:C26) | S26: =(SUM(G15:G26)-SUM(K15:K26))/SUM(G15:G26) | T26: =SUM(D15:D26)/SUM(B15:B26) | U26: =1/T26 | V26: =N26*S26/T26 | W26: =V26/R26 | X26: =R26/(N26*S26) | Y26: =G26-K26-P26 | Z26: =Y26/G26 | AA26: =Input_Data!G26 | AB26: =J26/AA26
A27: =Input_Data!A27 | B27: =F26 | C27: =Input_Data!C27 | D27: =Input_Data!D27 | E27: =C27-D27 | F27: =B27+E27 | G27: =Input_Data!B27 | H27: =G27/G26-1 | I27: =G27/G15-1 | J27: =G27*12 | K27: =Input_Data!E27 | L27: =G27-K27 | M27: =L27/G27 | N27: =G27/F27 | O27: =D27/B27 | P27: =Input_Data!F27 | Q27: =P27/C27 | R27: =SUM(P16:P27)/SUM(C16:C27) | S27: =(SUM(G16:G27)-SUM(K16:K27))/SUM(G16:G27) | T27: =SUM(D16:D27)/SUM(B16:B27) | U27: =1/T27 | V27: =N27*S27/T27 | W27: =V27/R27 | X27: =R27/(N27*S27) | Y27: =G27-K27-P27 | Z27: =Y27/G27 | AA27: =Input_Data!G27 | AB27: =J27/AA27
A28: =Input_Data!A28 | B28: =F27 | C28: =Input_Data!C28 | D28: =Input_Data!D28 | E28: =C28-D28 | F28: =B28+E28 | G28: =Input_Data!B28 | H28: =G28/G27-1 | I28: =G28/G16-1 | J28: =G28*12 | K28: =Input_Data!E28 | L28: =G28-K28 | M28: =L28/G28 | N28: =G28/F28 | O28: =D28/B28 | P28: =Input_Data!F28 | Q28: =P28/C28 | R28: =SUM(P17:P28)/SUM(C17:C28) | S28: =(SUM(G17:G28)-SUM(K17:K28))/SUM(G17:G28) | T28: =SUM(D17:D28)/SUM(B17:B28) | U28: =1/T28 | V28: =N28*S28/T28 | W28: =V28/R28 | X28: =R28/(N28*S28) | Y28: =G28-K28-P28 | Z28: =Y28/G28 | AA28: =Input_Data!G28 | AB28: =J28/AA28
... A40: =Input_Data!A40 | B40: =F39 | C40: =Input_Data!C40 | D40: =Input_Data!D40 | E40: =C40-D40 | F40: =B40+E40 | G40: =Input_Data!B40 | H40: =G40/G39-1 | I40: =G40/G28-1 | J40: =G40*12 | K40: =Input_Data!E40 | L40: =G40-K40 | M40: =L40/G40 | N40: =G40/F40 | O40: =D40/B40 | P40: =Input_Data!F40 | Q40: =P40/C40 | R40: =SUM(P29:P40)/SUM(C29:C40) | S40: =(SUM(G29:G40)-SUM(K29:K40))/SUM(G29:G40) | T40: =SUM(D29:D40)/SUM(B29:B40) | U40: =1/T40 | V40: =N40*S40/T40 | W40: =V40/R40 | X40: =R40/(N40*S40) | Y40: =G40-K40-P40 | Z40: =Y40/G40 | AA40: =Input_Data!G40 | AB40: =J40/AA40

Sheet Quarterly
A1: Quarterly summary
A2: Calendar quarters; magic number needs a prior quarter so 23Q4 is blank.
A4: Quarter | B4: Exit MRR | C4: Exit ARR | D4: QoQ growth | E4: Net new ARR | F4: S&M in quarter | G4: Magic number | H4: New logos | I4: Churned logos | J4: Ending customers | K4: Quarter revenue | L4: Quarter COGS | M4: Gross margin | N4: Contribution
A5: 23Q4 | B5: =Monthly_Metrics!G7 | C5: =B5*12 | F5: =SUM(Monthly_Metrics!P5:P7) | H5: =SUM(Monthly_Metrics!C5:C7) | I5: =SUM(Monthly_Metrics!D5:D7) | J5: =Monthly_Metrics!F7 | K5: =SUM(Monthly_Metrics!G5:G7) | L5: =SUM(Monthly_Metrics!K5:K7) | M5: =(K5-L5)/K5 | N5: =K5-L5-F5
A6: 24Q1 | B6: =Monthly_Metrics!G10 | C6: =B6*12 | D6: =B6/B5-1 | E6: =C6-C5 | F6: =SUM(Monthly_Metrics!P8:P10) | G6: =E6/F5 | H6: =SUM(Monthly_Metrics!C8:C10) | I6: =SUM(Monthly_Metrics!D8:D10) | J6: =Monthly_Metrics!F10 | K6: =SUM(Monthly_Metrics!G8:G10) | L6: =SUM(Monthly_Metrics!K8:K10) | M6: =(K6-L6)/K6 | N6: =K6-L6-F6
A7: 24Q2 | B7: =Monthly_Metrics!G13 | C7: =B7*12 | D7: =B7/B6-1 | E7: =C7-C6 | F7: =SUM(Monthly_Metrics!P11:P13) | G7: =E7/F6 | H7: =SUM(Monthly_Metrics!C11:C13) | I7: =SUM(Monthly_Metrics!D11:D13) | J7: =Monthly_Metrics!F13 | K7: =SUM(Monthly_Metrics!G11:G13) | L7: =SUM(Monthly_Metrics!K11:K13) | M7: =(K7-L7)/K7 | N7: =K7-L7-F7
A8: 24Q3 | B8: =Monthly_Metrics!G16 | C8: =B8*12 | D8: =B8/B7-1 | E8: =C8-C7 | F8: =SUM(Monthly_Metrics!P14:P16) | G8: =E8/F7 | H8: =SUM(Monthly_Metrics!C14:C16) | I8: =SUM(Monthly_Metrics!D14:D16) | J8: =Monthly_Metrics!F16 | K8: =SUM(Monthly_Metrics!G14:G16) | L8: =SUM(Monthly_Metrics!K14:K16) | M8: =(K8-L8)/K8 | N8: =K8-L8-F8
A9: 24Q4 | B9: =Monthly_Metrics!G19 | C9: =B9*12 | D9: =B9/B8-1 | E9: =C9-C8 | F9: =SUM(Monthly_Metrics!P17:P19) | G9: =E9/F8 | H9: =SUM(Monthly_Metrics!C17:C19) | I9: =SUM(Monthly_Metrics!D17:D19) | J9: =Monthly_Metrics!F19 | K9: =SUM(Monthly_Metrics!G17:G19) | L9: =SUM(Monthly_Metrics!K17:K19) | M9: =(K9-L9)/K9 | N9: =K9-L9-F9
A10: 25Q1 | B10: =Monthly_Metrics!G22 | C10: =B10*12 | D10: =B10/B9-1 | E10: =C10-C9 | F10: =SUM(Monthly_Metrics!P20:P22) | G10: =E10/F9 | H10: =SUM(Monthly_Metrics!C20:C22) | I10: =SUM(Monthly_Metrics!D20:D22) | J10: =Monthly_Metrics!F22 | K10: =SUM(Monthly_Metrics!G20:G22) | L10: =SUM(Monthly_Metrics!K20:K22) | M10: =(K10-L10)/K10 | N10: =K10-L10-F10
A11: 25Q2 | B11: =Monthly_Metrics!G25 | C11: =B11*12 | D11: =B11/B10-1 | E11: =C11-C10 | F11: =SUM(Monthly_Metrics!P23:P25) | G11: =E11/F10 | H11: =SUM(Monthly_Metrics!C23:C25) | I11: =SUM(Monthly_Metrics!D23:D25) | J11: =Monthly_Metrics!F25 | K11: =SUM(Monthly_Metrics!G23:G25) | L11: =SUM(Monthly_Metrics!K23:K25) | M11: =(K11-L11)/K11 | N11: =K11-L11-F11
A12: 25Q3 | B12: =Monthly_Metrics!G28 | C12: =B12*12 | D12: =B12/B11-1 | E12: =C12-C11 | F12: =SUM(Monthly_Metrics!P26:P28) | G12: =E12/F11 | H12: =SUM(Monthly_Metrics!C26:C28) | I12: =SUM(Monthly_Metrics!D26:D28) | J12: =Monthly_Metrics!F28 | K12: =SUM(Monthly_Metrics!G26:G28) | L12: =SUM(Monthly_Metrics!K26:K28) | M12: =(K12-L12)/K12 | N12: =K12-L12-F12
A13: 25Q4 | B13: =Monthly_Metrics!G31 | C13: =B13*12 | D13: =B13/B12-1 | E13: =C13-C12 | F13: =SUM(Monthly_Metrics!P29:P31) | G13: =E13/F12 | H13: =SUM(Monthly_Metrics!C29:C31) | I13: =SUM(Monthly_Metrics!D29:D31) | J13: =Monthly_Metrics!F31 | K13: =SUM(Monthly_Metrics!G29:G31) | L13: =SUM(Monthly_Metrics!K29:K31) | M13: =(K13-L13)/K13 | N13: =K13-L13-F13
A14: 26Q1 | B14: =Monthly_Metrics!G34 | C14: =B14*12 | D14: =B14/B13-1 | E14: =C14-C13 | F14: =SUM(Monthly_Metrics!P32:P34) | G14: =E14/F13 | H14: =SUM(Monthly_Metrics!C32:C34) | I14: =SUM(Monthly_Metrics!D32:D34) | J14: =Monthly_Metrics!F34 | K14: =SUM(Monthly_Metrics!G32:G34) | L14: =SUM(Monthly_Metrics!K32:K34) | M14: =(K14-L14)/K14 | N14: =K14-L14-F14
A15: 26Q2 | B15: =Monthly_Metrics!G37 | C15: =B15*12 | D15: =B15/B14-1 | E15: =C15-C14 | F15: =SUM(Monthly_Metrics!P35:P37) | G15: =E15/F14 | H15: =SUM(Monthly_Metrics!C35:C37) | I15: =SUM(Monthly_Metrics!D35:D37) | J15: =Monthly_Metrics!F37 | K15: =SUM(Monthly_Metrics!G35:G37) | L15: =SUM(Monthly_Metrics!K35:K37) | M15: =(K15-L15)/K15 | N15: =K15-L15-F15
A16: 26Q3 | B16: =Monthly_Metrics!G40 | C16: =B16*12 | D16: =B16/B15-1 | E16: =C16-C15 | F16: =SUM(Monthly_Metrics!P38:P40) | G16: =E16/F15 | H16: =SUM(Monthly_Metrics!C38:C40) | I16: =SUM(Monthly_Metrics!D38:D40) | J16: =Monthly_Metrics!F40 | K16: =SUM(Monthly_Metrics!G38:G40) | L16: =SUM(Monthly_Metrics!K38:K40) | M16: =(K16-L16)/K16 | N16: =K16-L16-F16

Sheet Unit_Economics
A1: Unit economics - as at 2026-09
A2: Headline block uses the house definitions. The sensitivity block shows what the same data yields under other common conventions.
A4: Metric | B4: Value | C4: Formula / definition
A5: MRR | B5: =Monthly_Metrics!G40 | C5: Latest month
A6: ARR | B6: =Monthly_Metrics!J40 | C6: MRR x 12
A7: YoY ARR growth | B7: =Monthly_Metrics!I40 | C7: vs same month last year
A8: Active customers | B8: =Monthly_Metrics!F40 | C8: Opening 120 + cumulative net adds
A9: ARPA | B9: =Monthly_Metrics!N40 | C9: MRR / period-end active customers
A10: Gross margin (month) | B10: =Monthly_Metrics!M40 | C10: (MRR - COGS) / MRR
A11: Gross margin (TTM) | B11: =Monthly_Metrics!S40 | C11: 12-month revenue-weighted
A12: Logo churn (month) | B12: =Monthly_Metrics!O40 | C12: Churned / opening customers
A13: Logo churn (TTM) | B13: =Monthly_Metrics!T40 | C13: Sum churned / sum opening, 12 months
A14: Implied customer life (months) | B14: =Monthly_Metrics!U40 | C14: 1 / TTM logo churn
A15: CAC (TTM) | B15: =Monthly_Metrics!R40 | C15: TTM S&M / TTM NEW customers
A16: LTV | B16: =Monthly_Metrics!V40 | C16: ARPA x TTM gross margin / TTM logo churn
A17: LTV : CAC | B17: =Monthly_Metrics!W40 | C17: Target >= 3.0 (Assumptions!B12)
A18: CAC payback (months) | B18: =Monthly_Metrics!X40 | C18: CAC / (ARPA x TTM gross margin)
A19: Magic number (latest quarter) | B19: =Quarterly!G16 | C19: Net new ARR / prior-quarter S&M
A20: Contribution margin (month) | B20: =Monthly_Metrics!Z40 | C20: (MRR - COGS - S&M) / MRR. NOT profit - opex is not in the source data.
A21: ARR per FTE | B21: =Monthly_Metrics!AB40 | C21: ARR / headcount
A24: Sensitivity: CAC under other conventions
A25: Convention | B25: Value | C25: Comment
A26: TTM S&M / TTM new logos (house definition) | B26: =SUM(Input_Data!F29:F40)/SUM(Input_Data!C29:C40) | C26: What we report. Measures the cost of acquiring a logo.
A27: TTM S&M / TTM NET adds | B27: =SUM(Input_Data!F29:F40)/(SUM(Input_Data!C29:C40)-SUM(Input_Data!D29:D40)) | C27: Blends acquisition and retention into one number; inflates CAC.
A28: Latest quarter S&M / latest quarter new logos | B28: =SUM(Input_Data!F38:F40)/SUM(Input_Data!C38:C40) | C28: More current, noisier.
A29: All-period S&M / all-period NET adds | B29: =SUM(Input_Data!F5:F40)/(SUM(Input_Data!C5:C40)-SUM(Input_Data!D5:D40)) | C29: The $1,583 on last quarter's slide 7 belongs to this family: S&M / NET adds over Feb-24 to Dec-25 gives $1,584.

Sheet Board_Recon
A1: Reconciliation to last quarter's board deck, slide 7
A2: Blue = as printed on the board deck. Computed column is live off this model.
A4: Metric | B4: Board deck | C4: Computed now | D4: Delta | E4: Verdict | F4: Explanation
A5: ARPA | B5: 236.27 | C5: =Unit_Economics!B9 | D5: =C5-B5 | E5: Ties out | F5: MRR / period-end active customers. Matches to the cent.
A6: CAC payback (months) | B6: 6.44 | C6: =Unit_Economics!B18 | D6: =C6-B6 | E6: Ties out | F6: CAC / (ARPA x TTM gross margin). Reproduces at CAC = $1,173 - not at the $1,583 on the same slide.
A7: CAC (trailing 12 months) | B7: 1583 | C7: =Unit_Economics!B15 | D7: =C7-B7 | E7: CONFLICT | F7: Slide overstates CAC by 35%. On S&M / NEW customers, every 12-month window in the dataset lands between $950 and $1,173 - $1,583 is not reachable. It is reproduced almost exactly by S&M / NET adds over Feb-24 to Dec-25 ($1,584): a stale window with churned logos netted out of the denominator.
A8: LTV | B8: 8019.93 | C8: =Unit_Economics!B16 | D8: =C8-B8 | E8: Definition gap | F8: 0.8% apart - convention, not error. The slide matches ARPA x TTM GM / simple average of monthly churn rates ($8,029); we use customer-weighted TTM churn. Both are defensible; use one.
A10: Bottom line: the $1,583 CAC on slide 7 is wrong on the data we now hold - it overstates customer acquisition cost by ~35%. The payback figure printed beside it (6.44 months) can only be reproduced with a CAC of ~$1,173, so the two numbers on that slide contradict each other. Everything downstream of CAC on that slide - LTV:CAC in particular - should be restated.

Sheet Projection
A1: 12-month illustrative projection
A2: Driver-based off Assumptions (blue cells there). Illustrative only - it is an extrapolation of the trailing year, not a plan or a forecast.
A4: Month | B4: Opening customers | C4: New logos | D4: Churned | E4: Closing customers | F4: ARPA | G4: MRR | H4: ARR | I4: Gross profit | J4: S&M spend | K4: Contribution (pre-opex)
A5: 2026-10 | B5: =Monthly_Metrics!F40 | C5: =ROUND(Monthly_Metrics!C40*(1+Assumptions!$B$6),0) | D5: =ROUND(B5*Assumptions!$B$7,0) | E5: =B5+C5-D5 | F5: =Monthly_Metrics!N40*(1+Assumptions!$B$8) | G5: =E5*F5 | H5: =G5*12 | I5: =G5*Assumptions!$B$9 | J5: =C5*Assumptions!$B$10 | K5: =I5-J5
A6: 2026-11 | B6: =E5 | C6: =ROUND(C5*(1+Assumptions!$B$6),0) | D6: =ROUND(B6*Assumptions!$B$7,0) | E6: =B6+C6-D6 | F6: =F5*(1+Assumptions!$B$8) | G6: =E6*F6 | H6: =G6*12 | I6: =G6*Assumptions!$B$9 | J6: =C6*Assumptions!$B$10 | K6: =I6-J6
A7: 2026-12 | B7: =E6 | C7: =ROUND(C6*(1+Assumptions!$B$6),0) | D7: =ROUND(B7*Assumptions!$B$7,0) | E7: =B7+C7-D7 | F7: =F6*(1+Assumptions!$B$8) | G7: =E7*F7 | H7: =G7*12 | I7: =G7*Assumptions!$B$9 | J7: =C7*Assumptions!$B$10 | K7: =I7-J7
A8: 2027-01 | B8: =E7 | C8: =ROUND(C7*(1+Assumptions!$B$6),0) | D8: =ROUND(B8*Assumptions!$B$7,0) | E8: =B8+C8-D8 | F8: =F7*(1+Assumptions!$B$8) | G8: =E8*F8 | H8: =G8*12 | I8: =G8*Assumptions!$B$9 | J8: =C8*Assumptions!$B$10 | K8: =I8-J8
A9: 2027-02 | B9: =E8 | C9: =ROUND(C8*(1+Assumptions!$B$6),0) | D9: =ROUND(B9*Assumptions!$B$7,0) | E9: =B9+C9-D9 | F9: =F8*(1+Assumptions!$B$8) | G9: =E9*F9 | H9: =G9*12 | I9: =G9*Assumptions!$B$9 | J9: =C9*Assumptions!$B$10 | K9: =I9-J9
A10: 2027-03 | B10: =E9 | C10: =ROUND(C9*(1+Assumptions!$B$6),0) | D10: =ROUND(B10*Assumptions!$B$7,0) | E10: =B10+C10-D10 | F10: =F9*(1+Assumptions!$B$8) | G10: =E10*F10 | H10: =G10*12 | I10: =G10*Assumptions!$B$9 | J10: =C10*Assumptions!$B$10 | K10: =I10-J10
A11: 2027-04 | B11: =E10 | C11: =ROUND(C10*(1+Assumptions!$B$6),0) | D11: =ROUND(B11*Assumptions!$B$7,0) | E11: =B11+C11-D11 | F11: =F10*(1+Assumptions!$B$8) | G11: =E11*F11 | H11: =G11*12 | I11: =G11*Assumptions!$B$9 | J11: =C11*Assumptions!$B$10 | K11: =I11-J11
A12: 2027-05 | B12: =E11 | C12: =ROUND(C11*(1+Assumptions!$B$6),0) | D12: =ROUND(B12*Assumptions!$B$7,0) | E12: =B12+C12-D12 | F12: =F11*(1+Assumptions!$B$8) | G12: =E12*F12 | H12: =G12*12 | I12: =G12*Assumptions!$B$9 | J12: =C12*Assumptions!$B$10 | K12: =I12-J12
A13: 2027-06 | B13: =E12 | C13: =ROUND(C12*(1+Assumptions!$B$6),0) | D13: =ROUND(B13*Assumptions!$B$7,0) | E13: =B13+C13-D13 | F13: =F12*(1+Assumptions!$B$8) | G13: =E13*F13 | H13: =G13*12 | I13: =G13*Assumptions!$B$9 | J13: =C13*Assumptions!$B$10 | K13: =I13-J13
A14: 2027-07 | B14: =E13 | C14: =ROUND(C13*(1+Assumptions!$B$6),0) | D14: =ROUND(B14*Assumptions!$B$7,0) | E14: =B14+C14-D14 | F14: =F13*(1+Assumptions!$B$8) | G14: =E14*F14 | H14: =G14*12 | I14: =G14*Assumptions!$B$9 | J14: =C14*Assumptions!$B$10 | K14: =I14-J14
A15: 2027-08 | B15: =E14 | C15: =ROUND(C14*(1+Assumptions!$B$6),0) | D15: =ROUND(B15*Assumptions!$B$7,0) | E15: =B15+C15-D15 | F15: =F14*(1+Assumptions!$B$8) | G15: =E15*F15 | H15: =G15*12 | I15: =G15*Assumptions!$B$9 | J15: =C15*Assumptions!$B$10 | K15: =I15-J15
A16: 2027-09 | B16: =E15 | C16: =ROUND(C15*(1+Assumptions!$B$6),0) | D16: =ROUND(B16*Assumptions!$B$7,0) | E16: =B16+C16-D16 | F16: =F15*(1+Assumptions!$B$8) | G16: =E16*F16 | H16: =G16*12 | I16: =G16*Assumptions!$B$9 | J16: =C16*Assumptions!$B$10 | K16: =I16-J16
A18: Contribution is MRR less COGS less S&M. R&D and G&A are absent from the source data, so this is not EBITDA and implies nothing about burn or runway.
