Workbook

Sheet Notes
B2: Bluebell SaaS Pte Ltd — Investor Update Model
B3: Period covered: Oct 2023 – Sep 2026 (36 months). Prepared 11 Sep 2026.
B4: Source: data/financials.xlsx (sheet 'raw'). All metrics on Monthly_Model / KPI_Summary are live formulas — change Raw_Data and everything recalculates.
B6: ASSUMPTIONS
B7: Starting customers | C7: 120 active customers at 30 Sep 2023 (given). Ending customers rolls forward: beginning + new − churned = 757 at 30 Sep 2026.
B8: Revenue | C8: MRR is treated as recognised monthly subscription revenue (no other revenue line provided). ARR = MRR × 12. No expansion/contraction split is available in the source data, so MRR-based net revenue retention cannot be computed; logo retention is used instead.
B9: Costs | C9: COGS and sales & marketing (S&M) spend are as provided. No other opex categories or payroll data were provided; headcount is shown for context. Contribution margin shown in the deck = TTM revenue − COGS − S&M.
B10: ARPA | C10: Month-end MRR ÷ active customers that month.
B11: Gross margin | C11: (TTM revenue − TTM COGS) ÷ TTM revenue on a rolling 12-month basis. Sep-2026: 77.14%.
B12: Logo churn | C12: Monthly = churned ÷ beginning customers. TTM steady-state = TTM churned ÷ sum of beginning customers; TTM average = average of the 12 monthly rates. LTV uses the average-monthly rate.
B13: CAC | C13: Headline CAC = TTM S&M ÷ gross new customers in the same 12 months ($1,172.91). A non-standard net-add variant = S&M ÷ (new − churned) is shown for transparency ($1,878.39 current; $1,578.59 at Aug 2025 — the figure on the prior board deck).
B14: LTV | C14: ARPA × gross margin ÷ monthly logo churn = $8,028.95. Alternative steady-state churn basis: $8,081.31. Both are simple steady-state approximations; no discounting.
B15: CAC payback | C15: CAC ÷ (ARPA × gross margin) = 6.44 months — gross profit per customer-month in the denominator.
B16: Sheet guide | C16: Raw_Data = verified copy of the source export. Monthly_Model = rollforward + monthly ratios + rolling-TTM unit economics (the formula engine). KPI_Summary = current vs end-Q2 snapshot. Slide7_Reconciliation = line-by-line check of the four figures on slide 7 of the Q2 board deck.

Sheet Raw_Data
A1: month | B1: mrr | C1: new_customers | D1: churned_customers | E1: cogs | F1: sales_marketing_spend | G1: headcount
A2: 2023-10 | B2: 22955.41 | C2: 14 | D2: 4 | E2: 6427.51 | F2: 12146.46 | G2: 9
A3: 2023-11 | B3: 25680.63 | C3: 14 | D3: 4 | E3: 7146.55 | F3: 13079.62 | G3: 10
A4: 2023-12 | B4: 27600.88 | C4: 17 | D4: 4 | E4: 7633.61 | F4: 15396.65 | G4: 10
A5: 2024-01 | B5: 29838.64 | C5: 15 | D5: 5 | E5: 8201.36 | F5: 13897.61 | G5: 11
A6: 2024-02 | B6: 31936.87 | C6: 15 | D6: 5 | E6: 8723.33 | F6: 14350.37 | G6: 12
A7: 2024-03 | B7: 34682.07 | C7: 18 | D7: 5 | E7: 9413.7 | F7: 17213.82 | G7: 13
A8: 2024-04 | B8: 37305.89 | C8: 20 | D8: 6 | E8: 10061.93 | F8: 19959.66 | G8: 13
A9: 2024-05 | B9: 40825.45 | C9: 20 | D9: 6 | E9: 10941.22 | F9: 18141.63 | G9: 14
A10: 2024-06 | B10: 44263.07 | C10: 22 | D10: 6 | E10: 11786.62 | F10: 19920.09 | G10: 15
A11: 2024-07 | B11: 47951.09 | C11: 19 | D11: 7 | E11: 12686.49 | F11: 18873.83 | G11: 15
A12: 2024-08 | B12: 51330.25 | C12: 23 | D12: 7 | E12: 13492.52 | F12: 22802.84 | G12: 16
A13: 2024-09 | B13: 54420.02 | C13: 24 | D13: 7 | E13: 14211.4 | F13: 24061.55 | G13: 17
... A37: 2026-09 | B37: 178857.07 | C37: 41 | D37: 15 | E37: 39348.56 | F37: 48686.47 | G37: 34

Sheet Monthly_Model
A1: Month | B1: MRR | C1: New customers | D1: Churned customers | E1: COGS | F1: S&M spend | G1: Headcount | H1: Beginning customers | I1: Ending customers | J1: Net adds | K1: ARR | L1: ARPA | M1: Monthly logo churn | N1: Gross profit | O1: Monthly GM% | P1: TTM revenue | Q1: TTM COGS | R1: TTM GM% | S1: TTM new | T1: TTM churned | U1: TTM S&M | V1: CAC (gross adds) | W1: TTM net adds | X1: CAC (net adds) | Y1: TTM churn — sum/sum | Z1: TTM churn — avg monthly | AA1: LTV | AB1: CAC payback (mo) | AC1: LTV / CAC
A2: 2023-10 | B2: =Raw_Data!B2 | C2: =Raw_Data!C2 | D2: =Raw_Data!D2 | E2: =Raw_Data!E2 | F2: =Raw_Data!F2 | G2: =Raw_Data!G2 | H2: 120 | I2: =H2+C2-D2 | J2: =C2-D2 | K2: =B2*12 | L2: =B2/I2 | M2: =D2/H2 | N2: =B2-E2 | O2: =(B2-E2)/B2
A3: 2023-11 | B3: =Raw_Data!B3 | C3: =Raw_Data!C3 | D3: =Raw_Data!D3 | E3: =Raw_Data!E3 | F3: =Raw_Data!F3 | G3: =Raw_Data!G3 | H3: =I2 | I3: =H3+C3-D3 | J3: =C3-D3 | K3: =B3*12 | L3: =B3/I3 | M3: =D3/H3 | N3: =B3-E3 | O3: =(B3-E3)/B3
A4: 2023-12 | B4: =Raw_Data!B4 | C4: =Raw_Data!C4 | D4: =Raw_Data!D4 | E4: =Raw_Data!E4 | F4: =Raw_Data!F4 | G4: =Raw_Data!G4 | H4: =I3 | I4: =H4+C4-D4 | J4: =C4-D4 | K4: =B4*12 | L4: =B4/I4 | M4: =D4/H4 | N4: =B4-E4 | O4: =(B4-E4)/B4
A5: 2024-01 | B5: =Raw_Data!B5 | C5: =Raw_Data!C5 | D5: =Raw_Data!D5 | E5: =Raw_Data!E5 | F5: =Raw_Data!F5 | G5: =Raw_Data!G5 | H5: =I4 | I5: =H5+C5-D5 | J5: =C5-D5 | K5: =B5*12 | L5: =B5/I5 | M5: =D5/H5 | N5: =B5-E5 | O5: =(B5-E5)/B5
A6: 2024-02 | B6: =Raw_Data!B6 | C6: =Raw_Data!C6 | D6: =Raw_Data!D6 | E6: =Raw_Data!E6 | F6: =Raw_Data!F6 | G6: =Raw_Data!G6 | H6: =I5 | I6: =H6+C6-D6 | J6: =C6-D6 | K6: =B6*12 | L6: =B6/I6 | M6: =D6/H6 | N6: =B6-E6 | O6: =(B6-E6)/B6
A7: 2024-03 | B7: =Raw_Data!B7 | C7: =Raw_Data!C7 | D7: =Raw_Data!D7 | E7: =Raw_Data!E7 | F7: =Raw_Data!F7 | G7: =Raw_Data!G7 | H7: =I6 | I7: =H7+C7-D7 | J7: =C7-D7 | K7: =B7*12 | L7: =B7/I7 | M7: =D7/H7 | N7: =B7-E7 | O7: =(B7-E7)/B7
A8: 2024-04 | B8: =Raw_Data!B8 | C8: =Raw_Data!C8 | D8: =Raw_Data!D8 | E8: =Raw_Data!E8 | F8: =Raw_Data!F8 | G8: =Raw_Data!G8 | H8: =I7 | I8: =H8+C8-D8 | J8: =C8-D8 | K8: =B8*12 | L8: =B8/I8 | M8: =D8/H8 | N8: =B8-E8 | O8: =(B8-E8)/B8
A9: 2024-05 | B9: =Raw_Data!B9 | C9: =Raw_Data!C9 | D9: =Raw_Data!D9 | E9: =Raw_Data!E9 | F9: =Raw_Data!F9 | G9: =Raw_Data!G9 | H9: =I8 | I9: =H9+C9-D9 | J9: =C9-D9 | K9: =B9*12 | L9: =B9/I9 | M9: =D9/H9 | N9: =B9-E9 | O9: =(B9-E9)/B9
A10: 2024-06 | B10: =Raw_Data!B10 | C10: =Raw_Data!C10 | D10: =Raw_Data!D10 | E10: =Raw_Data!E10 | F10: =Raw_Data!F10 | G10: =Raw_Data!G10 | H10: =I9 | I10: =H10+C10-D10 | J10: =C10-D10 | K10: =B10*12 | L10: =B10/I10 | M10: =D10/H10 | N10: =B10-E10 | O10: =(B10-E10)/B10
A11: 2024-07 | B11: =Raw_Data!B11 | C11: =Raw_Data!C11 | D11: =Raw_Data!D11 | E11: =Raw_Data!E11 | F11: =Raw_Data!F11 | G11: =Raw_Data!G11 | H11: =I10 | I11: =H11+C11-D11 | J11: =C11-D11 | K11: =B11*12 | L11: =B11/I11 | M11: =D11/H11 | N11: =B11-E11 | O11: =(B11-E11)/B11
A12: 2024-08 | B12: =Raw_Data!B12 | C12: =Raw_Data!C12 | D12: =Raw_Data!D12 | E12: =Raw_Data!E12 | F12: =Raw_Data!F12 | G12: =Raw_Data!G12 | H12: =I11 | I12: =H12+C12-D12 | J12: =C12-D12 | K12: =B12*12 | L12: =B12/I12 | M12: =D12/H12 | N12: =B12-E12 | O12: =(B12-E12)/B12
A13: 2024-09 | B13: =Raw_Data!B13 | C13: =Raw_Data!C13 | D13: =Raw_Data!D13 | E13: =Raw_Data!E13 | F13: =Raw_Data!F13 | G13: =Raw_Data!G13 | H13: =I12 | I13: =H13+C13-D13 | J13: =C13-D13 | K13: =B13*12 | L13: =B13/I13 | M13: =D13/H13 | N13: =B13-E13 | O13: =(B13-E13)/B13 | P13: =SUM(B2:B13) | Q13: =SUM(E2:E13) | R13: =1-Q13/P13 | S13: =SUM(C2:C13) | T13: =SUM(D2:D13) | U13: =SUM(F2:F13) | V13: =U13/S13 | W13: =S13-T13 | X13: =U13/W13 | Y13: =T13/SUM(H2:H13) | Z13: =AVERAGE(M2:M13) | AA13: =L13*R13/Z13 | AB13: =V13/(L13*R13) | AC13: =AA13/V13
A14: 2024-10 | B14: =Raw_Data!B14 | C14: =Raw_Data!C14 | D14: =Raw_Data!D14 | E14: =Raw_Data!E14 | F14: =Raw_Data!F14 | G14: =Raw_Data!G14 | H14: =I13 | I14: =H14+C14-D14 | J14: =C14-D14 | K14: =B14*12 | L14: =B14/I14 | M14: =D14/H14 | N14: =B14-E14 | O14: =(B14-E14)/B14 | P14: =SUM(B3:B14) | Q14: =SUM(E3:E14) | R14: =1-Q14/P14 | S14: =SUM(C3:C14) | T14: =SUM(D3:D14) | U14: =SUM(F3:F14) | V14: =U14/S14 | W14: =S14-T14 | X14: =U14/W14 | Y14: =T14/SUM(H3:H14) | Z14: =AVERAGE(M3:M14) | AA14: =L14*R14/Z14 | AB14: =V14/(L14*R14) | AC14: =AA14/V14
A15: 2024-11 | B15: =Raw_Data!B15 | C15: =Raw_Data!C15 | D15: =Raw_Data!D15 | E15: =Raw_Data!E15 | F15: =Raw_Data!F15 | G15: =Raw_Data!G15 | H15: =I14 | I15: =H15+C15-D15 | J15: =C15-D15 | K15: =B15*12 | L15: =B15/I15 | M15: =D15/H15 | N15: =B15-E15 | O15: =(B15-E15)/B15 | P15: =SUM(B4:B15) | Q15: =SUM(E4:E15) | R15: =1-Q15/P15 | S15: =SUM(C4:C15) | T15: =SUM(D4:D15) | U15: =SUM(F4:F15) | V15: =U15/S15 | W15: =S15-T15 | X15: =U15/W15 | Y15: =T15/SUM(H4:H15) | Z15: =AVERAGE(M4:M15) | AA15: =L15*R15/Z15 | AB15: =V15/(L15*R15) | AC15: =AA15/V15
A16: 2024-12 | B16: =Raw_Data!B16 | C16: =Raw_Data!C16 | D16: =Raw_Data!D16 | E16: =Raw_Data!E16 | F16: =Raw_Data!F16 | G16: =Raw_Data!G16 | H16: =I15 | I16: =H16+C16-D16 | J16: =C16-D16 | K16: =B16*12 | L16: =B16/I16 | M16: =D16/H16 | N16: =B16-E16 | O16: =(B16-E16)/B16 | P16: =SUM(B5:B16) | Q16: =SUM(E5:E16) | R16: =1-Q16/P16 | S16: =SUM(C5:C16) | T16: =SUM(D5:D16) | U16: =SUM(F5:F16) | V16: =U16/S16 | W16: =S16-T16 | X16: =U16/W16 | Y16: =T16/SUM(H5:H16) | Z16: =AVERAGE(M5:M16) | AA16: =L16*R16/Z16 | AB16: =V16/(L16*R16) | AC16: =AA16/V16
A17: 2025-01 | B17: =Raw_Data!B17 | C17: =Raw_Data!C17 | D17: =Raw_Data!D17 | E17: =Raw_Data!E17 | F17: =Raw_Data!F17 | G17: =Raw_Data!G17 | H17: =I16 | I17: =H17+C17-D17 | J17: =C17-D17 | K17: =B17*12 | L17: =B17/I17 | M17: =D17/H17 | N17: =B17-E17 | O17: =(B17-E17)/B17 | P17: =SUM(B6:B17) | Q17: =SUM(E6:E17) | R17: =1-Q17/P17 | S17: =SUM(C6:C17) | T17: =SUM(D6:D17) | U17: =SUM(F6:F17) | V17: =U17/S17 | W17: =S17-T17 | X17: =U17/W17 | Y17: =T17/SUM(H6:H17) | Z17: =AVERAGE(M6:M17) | AA17: =L17*R17/Z17 | AB17: =V17/(L17*R17) | AC17: =AA17/V17
A18: 2025-02 | B18: =Raw_Data!B18 | C18: =Raw_Data!C18 | D18: =Raw_Data!D18 | E18: =Raw_Data!E18 | F18: =Raw_Data!F18 | G18: =Raw_Data!G18 | H18: =I17 | I18: =H18+C18-D18 | J18: =C18-D18 | K18: =B18*12 | L18: =B18/I18 | M18: =D18/H18 | N18: =B18-E18 | O18: =(B18-E18)/B18 | P18: =SUM(B7:B18) | Q18: =SUM(E7:E18) | R18: =1-Q18/P18 | S18: =SUM(C7:C18) | T18: =SUM(D7:D18) | U18: =SUM(F7:F18) | V18: =U18/S18 | W18: =S18-T18 | X18: =U18/W18 | Y18: =T18/SUM(H7:H18) | Z18: =AVERAGE(M7:M18) | AA18: =L18*R18/Z18 | AB18: =V18/(L18*R18) | AC18: =AA18/V18
A19: 2025-03 | B19: =Raw_Data!B19 | C19: =Raw_Data!C19 | D19: =Raw_Data!D19 | E19: =Raw_Data!E19 | F19: =Raw_Data!F19 | G19: =Raw_Data!G19 | H19: =I18 | I19: =H19+C19-D19 | J19: =C19-D19 | K19: =B19*12 | L19: =B19/I19 | M19: =D19/H19 | N19: =B19-E19 | O19: =(B19-E19)/B19 | P19: =SUM(B8:B19) | Q19: =SUM(E8:E19) | R19: =1-Q19/P19 | S19: =SUM(C8:C19) | T19: =SUM(D8:D19) | U19: =SUM(F8:F19) | V19: =U19/S19 | W19: =S19-T19 | X19: =U19/W19 | Y19: =T19/SUM(H8:H19) | Z19: =AVERAGE(M8:M19) | AA19: =L19*R19/Z19 | AB19: =V19/(L19*R19) | AC19: =AA19/V19
A20: 2025-04 | B20: =Raw_Data!B20 | C20: =Raw_Data!C20 | D20: =Raw_Data!D20 | E20: =Raw_Data!E20 | F20: =Raw_Data!F20 | G20: =Raw_Data!G20 | H20: =I19 | I20: =H20+C20-D20 | J20: =C20-D20 | K20: =B20*12 | L20: =B20/I20 | M20: =D20/H20 | N20: =B20-E20 | O20: =(B20-E20)/B20 | P20: =SUM(B9:B20) | Q20: =SUM(E9:E20) | R20: =1-Q20/P20 | S20: =SUM(C9:C20) | T20: =SUM(D9:D20) | U20: =SUM(F9:F20) | V20: =U20/S20 | W20: =S20-T20 | X20: =U20/W20 | Y20: =T20/SUM(H9:H20) | Z20: =AVERAGE(M9:M20) | AA20: =L20*R20/Z20 | AB20: =V20/(L20*R20) | AC20: =AA20/V20
A21: 2025-05 | B21: =Raw_Data!B21 | C21: =Raw_Data!C21 | D21: =Raw_Data!D21 | E21: =Raw_Data!E21 | F21: =Raw_Data!F21 | G21: =Raw_Data!G21 | H21: =I20 | I21: =H21+C21-D21 | J21: =C21-D21 | K21: =B21*12 | L21: =B21/I21 | M21: =D21/H21 | N21: =B21-E21 | O21: =(B21-E21)/B21 | P21: =SUM(B10:B21) | Q21: =SUM(E10:E21) | R21: =1-Q21/P21 | S21: =SUM(C10:C21) | T21: =SUM(D10:D21) | U21: =SUM(F10:F21) | V21: =U21/S21 | W21: =S21-T21 | X21: =U21/W21 | Y21: =T21/SUM(H10:H21) | Z21: =AVERAGE(M10:M21) | AA21: =L21*R21/Z21 | AB21: =V21/(L21*R21) | AC21: =AA21/V21
A22: 2025-06 | B22: =Raw_Data!B22 | C22: =Raw_Data!C22 | D22: =Raw_Data!D22 | E22: =Raw_Data!E22 | F22: =Raw_Data!F22 | G22: =Raw_Data!G22 | H22: =I21 | I22: =H22+C22-D22 | J22: =C22-D22 | K22: =B22*12 | L22: =B22/I22 | M22: =D22/H22 | N22: =B22-E22 | O22: =(B22-E22)/B22 | P22: =SUM(B11:B22) | Q22: =SUM(E11:E22) | R22: =1-Q22/P22 | S22: =SUM(C11:C22) | T22: =SUM(D11:D22) | U22: =SUM(F11:F22) | V22: =U22/S22 | W22: =S22-T22 | X22: =U22/W22 | Y22: =T22/SUM(H11:H22) | Z22: =AVERAGE(M11:M22) | AA22: =L22*R22/Z22 | AB22: =V22/(L22*R22) | AC22: =AA22/V22
A23: 2025-07 | B23: =Raw_Data!B23 | C23: =Raw_Data!C23 | D23: =Raw_Data!D23 | E23: =Raw_Data!E23 | F23: =Raw_Data!F23 | G23: =Raw_Data!G23 | H23: =I22 | I23: =H23+C23-D23 | J23: =C23-D23 | K23: =B23*12 | L23: =B23/I23 | M23: =D23/H23 | N23: =B23-E23 | O23: =(B23-E23)/B23 | P23: =SUM(B12:B23) | Q23: =SUM(E12:E23) | R23: =1-Q23/P23 | S23: =SUM(C12:C23) | T23: =SUM(D12:D23) | U23: =SUM(F12:F23) | V23: =U23/S23 | W23: =S23-T23 | X23: =U23/W23 | Y23: =T23/SUM(H12:H23) | Z23: =AVERAGE(M12:M23) | AA23: =L23*R23/Z23 | AB23: =V23/(L23*R23) | AC23: =AA23/V23
A24: 2025-08 | B24: =Raw_Data!B24 | C24: =Raw_Data!C24 | D24: =Raw_Data!D24 | E24: =Raw_Data!E24 | F24: =Raw_Data!F24 | G24: =Raw_Data!G24 | H24: =I23 | I24: =H24+C24-D24 | J24: =C24-D24 | K24: =B24*12 | L24: =B24/I24 | M24: =D24/H24 | N24: =B24-E24 | O24: =(B24-E24)/B24 | P24: =SUM(B13:B24) | Q24: =SUM(E13:E24) | R24: =1-Q24/P24 | S24: =SUM(C13:C24) | T24: =SUM(D13:D24) | U24: =SUM(F13:F24) | V24: =U24/S24 | W24: =S24-T24 | X24: =U24/W24 | Y24: =T24/SUM(H13:H24) | Z24: =AVERAGE(M13:M24) | AA24: =L24*R24/Z24 | AB24: =V24/(L24*R24) | AC24: =AA24/V24
... A37: 2026-09 | B37: =Raw_Data!B37 | C37: =Raw_Data!C37 | D37: =Raw_Data!D37 | E37: =Raw_Data!E37 | F37: =Raw_Data!F37 | G37: =Raw_Data!G37 | H37: =I36 | I37: =H37+C37-D37 | J37: =C37-D37 | K37: =B37*12 | L37: =B37/I37 | M37: =D37/H37 | N37: =B37-E37 | O37: =(B37-E37)/B37 | P37: =SUM(B26:B37) | Q37: =SUM(E26:E37) | R37: =1-Q37/P37 | S37: =SUM(C26:C37) | T37: =SUM(D26:D37) | U37: =SUM(F26:F37) | V37: =U37/S37 | W37: =S37-T37 | X37: =U37/W37 | Y37: =T37/SUM(H26:H37) | Z37: =AVERAGE(M26:M37) | AA37: =L37*R37/Z37 | AB37: =V37/(L37*R37) | AC37: =AA37/V37

Sheet KPI_Summary
B2: KPI summary
B3: All values are live formulas from Monthly_Model. Sep 2026 = current month; Jun 2026 = end of last quarter (Q2).
B5: Metric | C5: 30 Sep 2026 (current) | D5: 30 Jun 2026 (end Q2) | E5: Definition
B6: Active customers | C6: =Monthly_Model!I37 | D6: =Monthly_Model!I34 | E6: Beginning + new − churned. Rollforward starts from 120 at Sep 2023.
B7: MRR | C7: =Monthly_Model!B37 | D7: =Monthly_Model!B34 | E7: Month-end monthly recurring revenue.
B8: ARR | C8: =Monthly_Model!K37 | D8: =Monthly_Model!K34 | E8: MRR × 12.
B9: MRR growth, year over year | C9: =Monthly_Model!B37/Monthly_Model!B25-1 | D9: =Monthly_Model!B34/Monthly_Model!B22-1 | E9: MRR vs same month a year earlier (Sep / Jun).
B10: MRR multiple since Oct 2023 | C10: =Monthly_Model!B37/Monthly_Model!B2 | E10: 7.79× over 36 months (6.04% monthly CAGR).
B11: New customers (TTM) | C11: =Monthly_Model!S37 | D11: =Monthly_Model!S34 | E11: Gross new logos in trailing 12 months: 434 (Q2: 401).
B12: Churned customers (TTM) | C12: =Monthly_Model!T37 | D12: =Monthly_Model!T34 | E12: Logos lost in trailing 12 months: 163 (Q2: 152).
B13: Net customer adds (TTM) | C13: =Monthly_Model!W37 | D13: =Monthly_Model!W34 | E13: New − churned, trailing 12 months.
B14: ARPA | C14: =Monthly_Model!L37 | D14: =Monthly_Model!L34 | E14: Month-end MRR ÷ ending active customers.
B15: Revenue (TTM) | C15: =Monthly_Model!P37 | D15: =Monthly_Model!P34 | E15: Sum of MRR, trailing 12 months.
B16: Gross margin (TTM) | C16: =Monthly_Model!R37 | D16: =Monthly_Model!R34 | E16: 1 − TTM COGS ÷ TTM revenue.
B17: S&M spend (TTM) | C17: =Monthly_Model!U37 | D17: =Monthly_Model!U34 | E17: Sales & marketing spend, trailing 12 months.
B18: CAC — gross adds (TTM) | C18: =Monthly_Model!V37 | D18: =Monthly_Model!V34 | E18: TTM S&M ÷ TTM new customers. Headline CAC.
B19: CAC — net adds (TTM) | C19: =Monthly_Model!X37 | D19: =Monthly_Model!X34 | E19: TTM S&M ÷ TTM net adds. Non-standard; shown because the Q2 board deck used it.
B20: Logo churn (TTM, avg monthly) | C20: =Monthly_Model!Z37 | D20: =Monthly_Model!Z34 | E20: Average of churned ÷ beginning customers over 12 months.
B21: Annualised logo retention | C21: =(1-Monthly_Model!Z37)^12 | D21: =(1-Monthly_Model!Z34)^12 | E21: (1 − monthly churn)^12. Logo basis — MRR NNR cannot be split from the source data.
B22: LTV | C22: =Monthly_Model!AA37 | D22: =Monthly_Model!AA34 | E22: ARPA × TTM gross margin ÷ avg monthly logo churn. Steady-state, undiscounted.
B23: CAC payback (months) | C23: =Monthly_Model!AB37 | D23: =Monthly_Model!AB34 | E23: CAC ÷ (ARPA × gross margin) — months of gross profit per customer.
B24: LTV / CAC | C24: =Monthly_Model!AC37 | D24: =Monthly_Model!AC34 | E24: Blended return on S&M using headline CAC.
B25: S&M intensity (TTM) | C25: =Monthly_Model!U37/Monthly_Model!P37 | D25: =Monthly_Model!U34/Monthly_Model!P34 | E25: TTM S&M ÷ TTM revenue.
B26: Headcount | C26: =Monthly_Model!G37 | D26: =Monthly_Model!G34 | E26: As reported; no payroll costs provided.
B27: ARR per employee | C27: =Monthly_Model!K37/Monthly_Model!G37 | D27: =Monthly_Model!K34/Monthly_Model!G34 | E27: Ending ARR ÷ headcount.

Sheet Slide7_Reconciliation
B2: Reconciliation — Q2 board deck, slide 7 ("Unit Economics")
B3: Board deck header says “Source: finance model, end of Q2”. Recomputed columns are live formulas from Monthly_Model.
B5: Metric | C5: Board slide 7 | D5: Recomputed 30 Sep 2026 | E5: Recomputed 30 Jun 2026 | F5: Finding | G5: Status
B6: ARPA | C6: 236.27 | D6: =Monthly_Model!L37 | E6: =Monthly_Model!L34 | F6: Matches the Sep-2026 cut EXACTLY ($236.2709). At end of Q2 the value was $235.13, so the slide is stamped “end of Q2” but carries a Q3 number. | G6: AGREES*
B7: CAC (trailing 12 months) | C7: 1583 | D7: =Monthly_Model!V37 | E7: =Monthly_Model!V34 | F7: CONFLICT. Headline CAC = TTM S&M ÷ GROSS new customers = $1,172.91 now ($1,157.02 at Q2). $1,583 only reproduces as S&M ÷ NET adds for a window around Aug 2025 ($1,578.59, see Monthly_Model!X24) — both the wrong denominator and a stale window. | G7: CONFLICT
B8: LTV | C8: 8019.93 | D8: =Monthly_Model!AA37 | E8: =Monthly_Model!AA34 | F8: Within $9 (0.1%) of the current-cut LTV of $8,028.95 (steady-state-churn variant: $8,081.31); the exact $8,019.93 does not reproduce under any tested window/method. End-Q2 LTV was $7,608.25, so this is also not an end-Q2 figure. Treat as current-quarter with a rounding/method difference to confirm. | G8: OFF ~0.1%
B9: CAC payback (months) | C9: 6.44 | D9: =Monthly_Model!AB37 | E9: =Monthly_Model!AB34 | F9: Matches the Sep-2026 cut EXACTLY ($1,172.91 ÷ ($236.27 × 77.14%) = 6.435 ≈ 6.44; end Q2 = 6.42). Note: this payback is internally inconsistent with the same slide's $1,583 CAC — it implies CAC of about $1,174 (cross-check below). | G9: AGREES*
B11: Cross-checks
B12: Net-add CAC at Aug 2025 (TTM) | C12: =Monthly_Model!X24 | D12: Closest reproduction of the board's $1,583: $1,578.59. Window ends 13 months before the slide date.
B13: Implied CAC from board payback | C13: =6.44*Monthly_Model!L37*Monthly_Model!R37 | D13: 6.44 × $236.27 × 77.14% = $1,173.81 — the board's payback implies the $1,173 gross-add CAC, not its own $1,583.
B14: LTV on steady-state churn (Sep 2026) | C14: =Monthly_Model!L37*Monthly_Model!R37/Monthly_Model!Y37 | D14: Alternative churn convention: TTM churned ÷ sum of beginning customers = 2.26%.
B16: * AGREES = reproduces on the current (Sep-2026) data; the board slide labels all figures “end of Q2”, but ARPA and payback tie to Sep 2026, not Jun 2026.
