Workbook

Sheet raw
A1: month | B1: mrr | C1: new_customers | D1: churned_customers | E1: cogs | F1: sales_marketing_spend | G1: headcount
A2: 2023-10 | B2: 22955.41 | C2: 14 | D2: 4 | E2: 6427.51 | F2: 12146.46 | G2: 9
A3: 2023-11 | B3: 25680.63 | C3: 14 | D3: 4 | E3: 7146.55 | F3: 13079.62 | G3: 10
A4: 2023-12 | B4: 27600.88 | C4: 17 | D4: 4 | E4: 7633.61 | F4: 15396.65 | G4: 10
A5: 2024-01 | B5: 29838.64 | C5: 15 | D5: 5 | E5: 8201.36 | F5: 13897.61 | G5: 11
A6: 2024-02 | B6: 31936.87 | C6: 15 | D6: 5 | E6: 8723.33 | F6: 14350.37 | G6: 12
A7: 2024-03 | B7: 34682.07 | C7: 18 | D7: 5 | E7: 9413.7 | F7: 17213.82 | G7: 13
A8: 2024-04 | B8: 37305.89 | C8: 20 | D8: 6 | E8: 10061.93 | F8: 19959.66 | G8: 13
A9: 2024-05 | B9: 40825.45 | C9: 20 | D9: 6 | E9: 10941.22 | F9: 18141.63 | G9: 14
A10: 2024-06 | B10: 44263.07 | C10: 22 | D10: 6 | E10: 11786.62 | F10: 19920.09 | G10: 15
A11: 2024-07 | B11: 47951.09 | C11: 19 | D11: 7 | E11: 12686.49 | F11: 18873.83 | G11: 15
A12: 2024-08 | B12: 51330.25 | C12: 23 | D12: 7 | E12: 13492.52 | F12: 22802.84 | G12: 16
A13: 2024-09 | B13: 54420.02 | C13: 24 | D13: 7 | E13: 14211.4 | F13: 24061.55 | G13: 17
... A37: 2026-09 | B37: 178857.07 | C37: 41 | D37: 15 | E37: 39348.56 | F37: 48686.47 | G37: 34

Sheet unit_economics
A1: Inputs
A2: Starting active customers | B2: 120
A4: month | B4: opening | C4: active | D4: gross_margin | E4: churn
A5: =raw!A2 | B5: =B2 | C5: =B5+raw!C2-raw!D2 | D5: =(raw!B2-raw!E2)/raw!B2 | E5: =raw!D2/B5
A6: =raw!A3 | B6: =C5 | C6: =B6+raw!C3-raw!D3 | D6: =(raw!B3-raw!E3)/raw!B3 | E6: =raw!D3/B6
A7: =raw!A4 | B7: =C6 | C7: =B7+raw!C4-raw!D4 | D7: =(raw!B4-raw!E4)/raw!B4 | E7: =raw!D4/B7
A8: =raw!A5 | B8: =C7 | C8: =B8+raw!C5-raw!D5 | D8: =(raw!B5-raw!E5)/raw!B5 | E8: =raw!D5/B8
A9: =raw!A6 | B9: =C8 | C9: =B9+raw!C6-raw!D6 | D9: =(raw!B6-raw!E6)/raw!B6 | E9: =raw!D6/B9
A10: =raw!A7 | B10: =C9 | C10: =B10+raw!C7-raw!D7 | D10: =(raw!B7-raw!E7)/raw!B7 | E10: =raw!D7/B10
A11: =raw!A8 | B11: =C10 | C11: =B11+raw!C8-raw!D8 | D11: =(raw!B8-raw!E8)/raw!B8 | E11: =raw!D8/B11
A12: =raw!A9 | B12: =C11 | C12: =B12+raw!C9-raw!D9 | D12: =(raw!B9-raw!E9)/raw!B9 | E12: =raw!D9/B12
A13: =raw!A10 | B13: =C12 | C13: =B13+raw!C10-raw!D10 | D13: =(raw!B10-raw!E10)/raw!B10 | E13: =raw!D10/B13
A14: =raw!A11 | B14: =C13 | C14: =B14+raw!C11-raw!D11 | D14: =(raw!B11-raw!E11)/raw!B11 | E14: =raw!D11/B14
A15: =raw!A12 | B15: =C14 | C15: =B15+raw!C12-raw!D12 | D15: =(raw!B12-raw!E12)/raw!B12 | E15: =raw!D12/B15
A16: =raw!A13 | B16: =C15 | C16: =B16+raw!C13-raw!D13 | D16: =(raw!B13-raw!E13)/raw!B13 | E16: =raw!D13/B16
A17: =raw!A14 | B17: =C16 | C17: =B17+raw!C14-raw!D14 | D17: =(raw!B14-raw!E14)/raw!B14 | E17: =raw!D14/B17
... A40: =raw!A37 | B40: =C39 | C40: =B40+raw!C37-raw!D37 | D40: =(raw!B37-raw!E37)/raw!B37 | E40: =raw!D37/B40
A42: CAC (TTM) | B42: =SUM(raw!F26:F37)/SUM(raw!C26:C37)
A43: ARPA | B43: =raw!B37/C40
A44: Avg gross margin (12m) | B44: =AVERAGE(D29:D40)
A45: Avg churn (12m) | B45: =AVERAGE(E29:E40)
A46: LTV | B46: =B43*B44/B45
A47: LTV/CAC | B47: =B46/B42
A48: CAC payback months | B48: =B42/(B43*B44)

Sheet dcf
A1: Assumptions
A2: Revenue year 0 | B2: =SUM(raw!B26:B37)
A3: Discount rate | B3: 0.12
A4: Initial investment | B4: -5000000
A5: Year | B5: 1 | C5: 2 | D5: 3 | E5: 4 | F5: 5
A6: Growth | B6: 0.25 | C6: 0.21 | D6: 0.17 | E6: 0.13 | F6: 0.1
A7: FCF margin | B7: 0.15 | C7: 0.175 | D7: 0.2 | E7: 0.225 | F7: 0.25
A9: Revenue | B9: =B2*(1+B6) | C9: =B9*(1+C6) | D9: =C9*(1+D6) | E9: =D9*(1+E6) | F9: =E9*(1+F6)
A10: FCF | B10: =B9*B7 | C10: =C9*C7 | D10: =D9*D7 | E10: =E9*E7 | F10: =F9*F7
A11: Cash flows | B11: =B4 | C11: =B10 | D11: =C10 | E11: =D10 | F11: =E10 | G11: =F10
A12: NPV | B12: =B4+NPV(B3,B10:F10)
A13: IRR | B13: =IRR(B11:G11)

Sheet loan
A1: Assumptions
A2: Principal | B2: 2000000
A3: Annual rate | B3: 0.07
A4: Payments | B4: 60
A5: Monthly payment (PMT) | B5: =PMT(B3/12,B4,-B2)
A7: Period | B7: Payment | C7: Interest | D7: Principal | E7: Balance
A8: 0 | E8: =B2
A9: 1 | B9: =$B$5 | C9: =E8*$B$3/12 | D9: =B9-C9 | E9: =E8-D9
A10: 2 | B10: =$B$5 | C10: =E9*$B$3/12 | D10: =B10-C10 | E10: =E9-D10
A11: 3 | B11: =$B$5 | C11: =E10*$B$3/12 | D11: =B11-C11 | E11: =E10-D11
A12: 4 | B12: =$B$5 | C12: =E11*$B$3/12 | D12: =B12-C12 | E12: =E11-D12
A13: 5 | B13: =$B$5 | C13: =E12*$B$3/12 | D13: =B13-C13 | E13: =E12-D13
A14: 6 | B14: =$B$5 | C14: =E13*$B$3/12 | D14: =B14-C14 | E14: =E13-D14
A15: 7 | B15: =$B$5 | C15: =E14*$B$3/12 | D15: =B15-C15 | E15: =E14-D15
A16: 8 | B16: =$B$5 | C16: =E15*$B$3/12 | D16: =B16-C16 | E16: =E15-D16
A17: 9 | B17: =$B$5 | C17: =E16*$B$3/12 | D17: =B17-C17 | E17: =E16-D17
A18: 10 | B18: =$B$5 | C18: =E17*$B$3/12 | D18: =B18-C18 | E18: =E17-D18
A19: 11 | B19: =$B$5 | C19: =E18*$B$3/12 | D19: =B19-C19 | E19: =E18-D19
A20: 12 | B20: =$B$5 | C20: =E19*$B$3/12 | D20: =B20-C20 | E20: =E19-D20
... A68: 60 | B68: =$B$5 | C68: =E67*$B$3/12 | D68: =B68-C68 | E68: =E67-D68
A70: Total interest | B70: =SUM(C9:C68)
