Workbook

Sheet raw
A1: month | B1: mrr | C1: new_customers | D1: churned_customers | E1: cogs | F1: sales_marketing_spend | G1: headcount
A2: 2023-10 | B2: 22955.41 | C2: 14 | D2: 4 | E2: 6427.51 | F2: 12146.46 | G2: 9
A3: 2023-11 | B3: 25680.63 | C3: 14 | D3: 4 | E3: 7146.55 | F3: 13079.62 | G3: 10
A4: 2023-12 | B4: 27600.88 | C4: 17 | D4: 4 | E4: 7633.61 | F4: 15396.65 | G4: 10
A5: 2024-01 | B5: 29838.64 | C5: 15 | D5: 5 | E5: 8201.36 | F5: 13897.61 | G5: 11
A6: 2024-02 | B6: 31936.87 | C6: 15 | D6: 5 | E6: 8723.33 | F6: 14350.37 | G6: 12
A7: 2024-03 | B7: 34682.07 | C7: 18 | D7: 5 | E7: 9413.7 | F7: 17213.82 | G7: 13
A8: 2024-04 | B8: 37305.89 | C8: 20 | D8: 6 | E8: 10061.93 | F8: 19959.66 | G8: 13
A9: 2024-05 | B9: 40825.45 | C9: 20 | D9: 6 | E9: 10941.22 | F9: 18141.63 | G9: 14
A10: 2024-06 | B10: 44263.07 | C10: 22 | D10: 6 | E10: 11786.62 | F10: 19920.09 | G10: 15
A11: 2024-07 | B11: 47951.09 | C11: 19 | D11: 7 | E11: 12686.49 | F11: 18873.83 | G11: 15
A12: 2024-08 | B12: 51330.25 | C12: 23 | D12: 7 | E12: 13492.52 | F12: 22802.84 | G12: 16
A13: 2024-09 | B13: 54420.02 | C13: 24 | D13: 7 | E13: 14211.4 | F13: 24061.55 | G13: 17
... A37: 2026-09 | B37: 178857.07 | C37: 41 | D37: 15 | E37: 39348.56 | F37: 48686.47 | G37: 34

Sheet unit_economics
A1: month | B1: active_customers | C1: gross_margin | D1: monthly_churn
A2: =raw!A2 | B2: =120+raw!C2-raw!D2 | C2: =(raw!B2-raw!E2)/raw!B2 | D2: =raw!D2/120
A3: =raw!A3 | B3: =B2+raw!C3-raw!D3 | C3: =(raw!B3-raw!E3)/raw!B3 | D3: =raw!D3/B2
A4: =raw!A4 | B4: =B3+raw!C4-raw!D4 | C4: =(raw!B4-raw!E4)/raw!B4 | D4: =raw!D4/B3
A5: =raw!A5 | B5: =B4+raw!C5-raw!D5 | C5: =(raw!B5-raw!E5)/raw!B5 | D5: =raw!D5/B4
A6: =raw!A6 | B6: =B5+raw!C6-raw!D6 | C6: =(raw!B6-raw!E6)/raw!B6 | D6: =raw!D6/B5
A7: =raw!A7 | B7: =B6+raw!C7-raw!D7 | C7: =(raw!B7-raw!E7)/raw!B7 | D7: =raw!D7/B6
A8: =raw!A8 | B8: =B7+raw!C8-raw!D8 | C8: =(raw!B8-raw!E8)/raw!B8 | D8: =raw!D8/B7
A9: =raw!A9 | B9: =B8+raw!C9-raw!D9 | C9: =(raw!B9-raw!E9)/raw!B9 | D9: =raw!D9/B8
A10: =raw!A10 | B10: =B9+raw!C10-raw!D10 | C10: =(raw!B10-raw!E10)/raw!B10 | D10: =raw!D10/B9
A11: =raw!A11 | B11: =B10+raw!C11-raw!D11 | C11: =(raw!B11-raw!E11)/raw!B11 | D11: =raw!D11/B10
A12: =raw!A12 | B12: =B11+raw!C12-raw!D12 | C12: =(raw!B12-raw!E12)/raw!B12 | D12: =raw!D12/B11
A13: =raw!A13 | B13: =B12+raw!C13-raw!D13 | C13: =(raw!B13-raw!E13)/raw!B13 | D13: =raw!D13/B12
A14: =raw!A14 | B14: =B13+raw!C14-raw!D14 | C14: =(raw!B14-raw!E14)/raw!B14 | D14: =raw!D14/B13
... A37: =raw!A37 | B37: =B36+raw!C37-raw!D37 | C37: =(raw!B37-raw!E37)/raw!B37 | D37: =raw!D37/B36
A40: Metric | B40: Value
A41: CAC (trailing 12m) | B41: =SUM(raw!F26:F37)/SUM(raw!C26:C37)
A42: ARPA | B42: =raw!B37/(120+SUM(raw!C2:C37)-SUM(raw!D2:D37))
A43: Avg gross margin (last 12m) | B43: =AVERAGE(C26:C37)
A44: Avg monthly churn (last 12m) | B44: =AVERAGE(D26:D37)
A45: LTV | B45: =B42*B43/B44
A46: LTV / CAC | B46: =B45/B41
A47: CAC payback (months) | B47: =B41/(B42*B43)

Sheet dcf
A1: DCF Model
A3: Assumptions
A4: Revenue (year 0) | B4: =SUM(raw!B26:B37)
A5: Discount rate | B5: 0.12
A6: Initial investment (year 0) | B6: -5000000
A8: Year | B8: Growth | C8: FCF margin
A9: Year 1 | B9: 0.25 | C9: 0.15
A10: Year 2 | B10: 0.21 | C10: 0.175
A11: Year 3 | B11: 0.17 | C11: 0.2
A12: Year 4 | B12: 0.13 | C12: 0.225
A13: Year 5 | B13: 0.1 | C13: 0.25
A15: Year | B15: Revenue | C15: FCF
A16: Year 0 | B16: =B4 | C16: =B6
A17: Year 1 | B17: =B16*(1+B9) | C17: =B17*C9
A18: Year 2 | B18: =B17*(1+B10) | C18: =B18*C10
A19: Year 3 | B19: =B18*(1+B11) | C19: =B19*C11
A20: Year 4 | B20: =B19*(1+B12) | C20: =B20*C12
A21: Year 5 | B21: =B20*(1+B13) | C21: =B21*C13
A23: NPV | B23: =C16+NPV(B5,C17:C21)
A24: IRR | B24: =IRR(C16:C21)

Sheet loan
A1: Loan Amortization
A3: Principal | B3: 2000000
A4: Annual interest rate | B4: 0.07
A5: Monthly interest rate | B5: =B4/12
A6: Term (months) | B6: 60
A7: Monthly payment | B7: =B3*B5/(1-(1+B5)^-B6)
A8: Total interest | B8: =B7*B6-B3
A10: Month | B10: Beginning balance | C10: Payment | D10: Interest | E10: Principal | F10: Ending balance
A11: 1 | B11: =$B$3 | C11: =$B$7 | D11: =B11*$B$5 | E11: =C11-D11 | F11: =B11-E11
A12: 2 | B12: =F11 | C12: =$B$7 | D12: =B12*$B$5 | E12: =C12-D12 | F12: =B12-E12
A13: 3 | B13: =F12 | C13: =$B$7 | D13: =B13*$B$5 | E13: =C13-D13 | F13: =B13-E13
A14: 4 | B14: =F13 | C14: =$B$7 | D14: =B14*$B$5 | E14: =C14-D14 | F14: =B14-E14
A15: 5 | B15: =F14 | C15: =$B$7 | D15: =B15*$B$5 | E15: =C15-D15 | F15: =B15-E15
A16: 6 | B16: =F15 | C16: =$B$7 | D16: =B16*$B$5 | E16: =C16-D16 | F16: =B16-E16
A17: 7 | B17: =F16 | C17: =$B$7 | D17: =B17*$B$5 | E17: =C17-D17 | F17: =B17-E17
A18: 8 | B18: =F17 | C18: =$B$7 | D18: =B18*$B$5 | E18: =C18-D18 | F18: =B18-E18
A19: 9 | B19: =F18 | C19: =$B$7 | D19: =B19*$B$5 | E19: =C19-D19 | F19: =B19-E19
A20: 10 | B20: =F19 | C20: =$B$7 | D20: =B20*$B$5 | E20: =C20-D20 | F20: =B20-E20
A21: 11 | B21: =F20 | C21: =$B$7 | D21: =B21*$B$5 | E21: =C21-D21 | F21: =B21-E21
A22: 12 | B22: =F21 | C22: =$B$7 | D22: =B22*$B$5 | E22: =C22-D22 | F22: =B22-E22
A23: 13 | B23: =F22 | C23: =$B$7 | D23: =B23*$B$5 | E23: =C23-D23 | F23: =B23-E23
... A70: 60 | B70: =F69 | C70: =$B$7 | D70: =B70*$B$5 | E70: =C70-D70 | F70: =B70-E70
